{
    "average_errors_by_distance": {
        "100": {
            "translational_error_percent": 2.465,
            "rotational_error_deg_per_100m": -2.461
        },
        "200": {
            "translational_error_percent": 3.248,
            "rotational_error_deg_per_100m": -2.395
        },
        "300": {
            "translational_error_percent": 4.963,
            "rotational_error_deg_per_100m": -2.566
        },
        "400": {
            "translational_error_percent": 5.738,
            "rotational_error_deg_per_100m": -2.585
        },
        "500": {
            "translational_error_percent": 7.072,
            "rotational_error_deg_per_100m": -2.421
        },
        "600": {
            "translational_error_percent": 8.093,
            "rotational_error_deg_per_100m": -2.4
        },
        "700": {
            "translational_error_percent": 9.012,
            "rotational_error_deg_per_100m": -2.269
        }
    },
    "overall_average_errors": {
        "translational_error_percent": 4.332,
        "rotational_error_deg_per_100m": 2.471,
        "root_mean_square_error_percent": 3.315
    }
}