{
    "average_errors_by_distance": {
        "100": {
            "translational_error_percent": 2.903,
            "rotational_error_deg_per_100m": -1.69
        },
        "200": {
            "translational_error_percent": 3.406,
            "rotational_error_deg_per_100m": -1.422
        },
        "300": {
            "translational_error_percent": 5.124,
            "rotational_error_deg_per_100m": -2.05
        },
        "400": {
            "translational_error_percent": 7.034,
            "rotational_error_deg_per_100m": -2.3
        },
        "500": {
            "translational_error_percent": 7.518,
            "rotational_error_deg_per_100m": -1.907
        },
        "600": {
            "translational_error_percent": 7.872,
            "rotational_error_deg_per_100m": -1.673
        },
        "700": {
            "translational_error_percent": 8.546,
            "rotational_error_deg_per_100m": -1.904
        }
    },
    "overall_average_errors": {
        "translational_error_percent": 4.712,
        "rotational_error_deg_per_100m": 1.786,
        "root_mean_square_error_percent": 3.275
    }
}